django_clickhouse_logger/__init__.py
django_clickhouse_logger/clickhouse.py
django_clickhouse_logger/db.py
django_clickhouse_logger/functions.py
django_clickhouse_logger/handlers.py
django_clickhouse_logger/settings.py
django_clickhouse_logger/utils.py
django_clickhouse_logger/proxy/__init__.py
django_clickhouse_logger/proxy/clickhouse.py
django_clickhouse_logger-0.3.2.dist-info/LICENSE
django_clickhouse_logger-0.3.2.dist-info/METADATA
django_clickhouse_logger-0.3.2.dist-info/WHEEL
django_clickhouse_logger-0.3.2.dist-info/top_level.txt
django_clickhouse_logger-0.3.2.dist-info/RECORD
