Metadata-Version: 2.1
Name: django-clickhouse-logger
Version: 0.3.2
Summary: Logging Django errors & capture exceptions to the clickhouse database with daily rotation.
Home-page: https://github.com/Sobolev5/django-clickhouse-logger/
Author: Sobolev Andrey
Author-email: email.asobolev@gmail.com
License: UNKNOWN
Platform: UNKNOWN
Classifier: Programming Language :: Python :: 3
Classifier: License :: OSI Approved :: MIT License
Classifier: Operating System :: OS Independent
Requires-Python: >=3.8
License-File: LICENSE
Requires-Dist: clickhouse-driver (==0.2.4)
Requires-Dist: shortuuid (==1.0.9)
Requires-Dist: simple-print (>=1.4.9)
